libnetfilter/__init__.py
libnetfilter/conntrack/__init__.py
libnetfilter/conntrack/libnetfilter_conntrack.py
libnetfilter/log/__init__.py
libnetfilter/log/libnetfilter_log.py
libnetfilter/netlink/__init__.py
libnetfilter/netlink/libnfnetlink.py
libnetfilter/queue/__init__.py
libnetfilter/queue/libnetfilter_queue.py
libnetfilter-0.1.0.post1.dist-info/WHEEL
libnetfilter-0.1.0.post1.dist-info/METADATA
libnetfilter-0.1.0.post1.dist-info/RECORD
