Metadata-Version: 2.1
Name: libnetfilter
Version: 0.1.0.post1
Summary: Python wrapper (partial) around libnetfilter libraries
Home-page: https://gitlab.com/python-utils2/libnetfilter
Author: Mark Bools
Author-email: mark@saltyvagrant.com
Requires-Python: >=3.4,<4.0
Classifier: Development Status :: 3 - Alpha
Classifier: Intended Audience :: Developers
Classifier: Programming Language :: Python :: 3
Classifier: Programming Language :: Python :: 3.4
Classifier: Programming Language :: Python :: 3.5
Classifier: Programming Language :: Python :: 3.6
Classifier: Programming Language :: Python :: 3.7
Classifier: Programming Language :: Python :: 3.8
Classifier: Topic :: Software Development :: Libraries :: Python Modules
Classifier: Topic :: System :: Networking :: Firewalls
